llm_tool_registry/__init__.py
llm_tool_registry/_registry.py
llm_tool_registry-0.1.1.dist-info/METADATA
llm_tool_registry-0.1.1.dist-info/WHEEL
llm_tool_registry-0.1.1.dist-info/entry_points.txt
llm_tool_registry-0.1.1.dist-info/RECORD
