Metadata-Version: 2.3
Name: llm_tool_registry
Version: 0.1.1
Summary: Implements a tool registry to make tool calling easier when using LLMs
Author-email: Robert Heyer <bobby.heyer@gmail.com>
Requires-Python: >=3.9
Requires-Dist: docstring-parser>=0.16
